dankcli/__init__.py
dankcli/__main__.py
dankcli/functions.py
dankcli/fonts/HelveticaNeue.ttf
dankcli/fonts/arial.ttf
dankcli-0.5.8.dist-info/LICENSE
dankcli-0.5.8.dist-info/METADATA
dankcli-0.5.8.dist-info/WHEEL
dankcli-0.5.8.dist-info/top_level.txt
dankcli-0.5.8.dist-info/RECORD
