Metadata-Version: 2.1
Name: dankcli
Version: 0.5.8
Summary: CLI Meme Generator to automatically add whitespace and text to top
Home-page: https://github.com/sggts04/dankcli
Author: Shreyas Gupta
Author-email: technology.shreyas@gmail.com
License: MIT
Keywords: dankcli dank meme memegenerator memes generator pillow dankmemes
Platform: UNKNOWN
Requires-Dist: pillow
